giturl.py
giturl.py-0.2.1.dist-info/top_level.txt
giturl.py-0.2.1.dist-info/RECORD
giturl.py-0.2.1.dist-info/WHEEL
giturl.py-0.2.1.dist-info/metadata.json
giturl.py-0.2.1.dist-info/METADATA
giturl.py-0.2.1.dist-info/DESCRIPTION.rst
