Metadata-Version: 2.0
Name: giturl.py
Version: 0.2.1
Summary: A tool for parsing all sorts of Git URLs
Home-page: https://github.com/willyg302/giturl
Author: William Gaul
Author-email: willyg302@gmail.com
License: MIT
Platform: UNKNOWN
Classifier: License :: OSI Approved :: MIT License
Classifier: Programming Language :: Python :: 2.7
Classifier: Programming Language :: Python :: 3.4
